openstack_ansible_wizard/__init__.py
openstack_ansible_wizard/app.py
openstack_ansible_wizard/common/config.py
openstack_ansible_wizard/common/git.py
openstack_ansible_wizard/common/screens.py
openstack_ansible_wizard/common/utils.py
openstack_ansible_wizard/css/openstack_ansible_ui.tcss
openstack_ansible_wizard/extensions/button.py
openstack_ansible_wizard/extensions/textarea.py
openstack_ansible_wizard/screens/__init__.py
openstack_ansible_wizard/screens/bootstrap.py
openstack_ansible_wizard/screens/editor.py
openstack_ansible_wizard/screens/git.py
openstack_ansible_wizard/screens/initial.py
openstack_ansible_wizard/screens/inventory.py
openstack_ansible_wizard/screens/networks.py
openstack_ansible_wizard/screens/service.py
openstack_ansible_wizard/screens/services/__init__.py
openstack_ansible_wizard/screens/services/generic.py
openstack_ansible_wizard/screens/services/haproxy.py
openstack_ansible_wizard/tests/__init__.py
openstack_ansible_wizard-0.1.1.dist-info/licenses/LICENSE
openstack_ansible_wizard-0.1.1.dist-info/METADATA
openstack_ansible_wizard-0.1.1.dist-info/WHEEL
openstack_ansible_wizard-0.1.1.dist-info/entry_points.txt
openstack_ansible_wizard-0.1.1.dist-info/top_level.txt
openstack_ansible_wizard-0.1.1.dist-info/RECORD
