Metadata-Version: 2.4
Name: openstack-ansible-wizard
Version: 0.1.1
Summary: A Textual-based Wizard for OpenStack-Ansible.
Author-email: Adria Cloud Services <contact@adria-cloud.com>
License:                                  Apache License
Project-URL: Homepage, https://github.com/adriacloud/openstack-ansible-wizard
Project-URL: Bug Tracker, https://github.com/adriacloud/openstack-ansible-wizard/issues
Keywords: openstack,ansible,tui,textual
Classifier: Development Status :: 3 - Alpha
Classifier: Programming Language :: Python :: 3
Classifier: Programming Language :: Python :: 3.10
Classifier: Programming Language :: Python :: 3.11
Classifier: Programming Language :: Python :: 3.12
Classifier: Programming Language :: Python :: 3.13
Classifier: License :: OSI Approved :: Apache Software License
Classifier: Operating System :: OS Independent
Classifier: Topic :: System :: Installation/Setup
Requires-Python: >=3.10
License-File: LICENSE
Requires-Dist: textual[syntax]<7.0,>=6.0
Requires-Dist: PyYAML>=3.12
Requires-Dist: ruamel.yaml>=0.18.15
Requires-Dist: GitPython>=1.0.1
Requires-Dist: tree-sitter<0.26
Provides-Extra: serve
Requires-Dist: textual-serve; extra == "serve"
Dynamic: license-file
